README.md
setup.py
cythereal_dashboard/__init__.py
cythereal_dashboard/api_client.py
cythereal_dashboard/configuration.py
cythereal_dashboard/rest.py
cythereal_dashboard.egg-info/PKG-INFO
cythereal_dashboard.egg-info/SOURCES.txt
cythereal_dashboard.egg-info/dependency_links.txt
cythereal_dashboard.egg-info/requires.txt
cythereal_dashboard.egg-info/top_level.txt
cythereal_dashboard/api/__init__.py
cythereal_dashboard/api/alerts_api.py
cythereal_dashboard/api/binaries_api.py
cythereal_dashboard/api/campaigns_api.py
cythereal_dashboard/api/charts_api.py
cythereal_dashboard/api/configs_api.py
cythereal_dashboard/api/dashboard_api.py
cythereal_dashboard/api/emails_api.py
cythereal_dashboard/api/files_api.py
cythereal_dashboard/api/investigations_api.py
cythereal_dashboard/api/iocs_api.py
cythereal_dashboard/api/logs_api.py
cythereal_dashboard/api/reports_api.py
cythereal_dashboard/api/reprocess_api.py
cythereal_dashboard/api/signatures_api.py
cythereal_dashboard/api/tables_api.py
cythereal_dashboard/api/tags_api.py
cythereal_dashboard/api/update_api.py
cythereal_dashboard/api/workspaces_api.py
cythereal_dashboard/models/__init__.py
cythereal_dashboard/models/add_to_investigation.py
cythereal_dashboard/models/add_to_investigation_response.py
cythereal_dashboard/models/alert.py
cythereal_dashboard/models/alert_created.py
cythereal_dashboard/models/alert_email_sent.py
cythereal_dashboard/models/alert_exists.py
cythereal_dashboard/models/alert_list.py
cythereal_dashboard/models/alert_list_response.py
cythereal_dashboard/models/alert_model.py
cythereal_dashboard/models/analysis.py
cythereal_dashboard/models/analysis_inner.py
cythereal_dashboard/models/api_response.py
cythereal_dashboard/models/archive_list_response.py
cythereal_dashboard/models/archive_report.py
cythereal_dashboard/models/archive_report_children.py
cythereal_dashboard/models/archive_report_response.py
cythereal_dashboard/models/av_names.py
cythereal_dashboard/models/binary.py
cythereal_dashboard/models/binary_graph_list.py
cythereal_dashboard/models/binary_graph_list_response.py
cythereal_dashboard/models/binary_graph_model.py
cythereal_dashboard/models/binary_list.py
cythereal_dashboard/models/binary_list_response.py
