Metadata-Version: 1.0
Name: cythereal-dashboard
Version: 0.42.1
Summary: Cythereal Dashboard API
Home-page: UNKNOWN
Author: UNKNOWN
Author-email: support@cythereal.com
License: UNKNOWN
Keywords: Swagger,Cythereal Dashboard API
Platform: UNKNOWN
